[
  {
    "order_id": "ORD-2026-01-12-S05-0001",
    "store_id": "STORE05",
    "order_date": "2026-01-12",
    "order_time": "19:44:37",
    "customer_id": "98a547b2-09a1-4b34-b111-84e79c4c37b3",
    "items": [
      {
        "sku": "SKU00029",
        "product_name": "Nettoyant Poids",
        "quantity": 5
      },
      {
        "sku": "SKU00019",
        "product_name": "Liquide vaisselle Baisser",
        "quantity": 2
      },
      {
        "sku": "SKU00036",
        "product_name": "Crème Étage",
        "quantity": 1
      },
      {
        "sku": "SKU00021",
        "product_name": "Bananes Bien",
        "quantity": 2
      }
    ]
  },
  {
    "order_id": "ORD-2026-01-12-S05-0002",
    "store_id": "STORE05",
    "order_date": "2026-01-12",
    "order_time": "12:43:40",
    "customer_id": "9caf4bfe-7ff8-42c6-b79a-566b2e1482be",
    "items": [
      {
        "sku": "SKU00056",
        "product_name": "Lait infantile Chien",
        "quantity": 5
      },
      {
        "sku": "SKU00048",
        "product_name": "Biscuits Avancer",
        "quantity": 1
      },
      {
        "sku": "SKU00099",
        "product_name": "Poulet Gauche",
        "quantity": 1
      },
      {
        "sku": "SKU00086",
        "product_name": "Éponges Manier",
        "quantity": 3
      },
      {
        "sku": "SKU00057",
        "product_name": "Lait Étrange",
        "quantity": 3
      },
      {
        "sku": "SKU00028",
        "product_name": "Carottes Tranquille",
        "quantity": 5
      }
    ]
  },
  {
    "order_id": "ORD-2026-01-12-S05-0003",
    "store_id": "STORE05",
    "order_date": "2026-01-12",
    "order_time": "14:28:01",
    "customer_id": "d3946dc7-a08f-41c6-9688-8e84f346bbe7",
    "items": [
      {
        "sku": "SKU00018",
        "product_name": "Liquide vaisselle Sourire",
        "quantity": 4
      },
      {
        "sku": "SKU00088",
        "product_name": "Yaourt Mémoire",
        "quantity": 5
      },
      {
        "sku": "SKU00063",
        "product_name": "Thé Nommer",
        "quantity": 2
      },
      {
        "sku": "SKU00041",
        "product_name": "Crème Chair",
        "quantity": 1
      },
      {
        "sku": "SKU00014",
        "product_name": "Eau En",
        "quantity": 5
      },
      {
        "sku": "SKU00096",
        "product_name": "Lessive Point",
        "quantity": 3
      },
      {
        "sku": "SKU00037",
        "product_name": "Chocolat Peur",
        "quantity": 5
      },
      {
        "sku": "SKU00068",
        "product_name": "Crème Bras",
        "quantity": 4
      },
      {
        "sku": "SKU00092",
        "product_name": "Shampoing Nord",
        "quantity": 2
      },
      {
        "sku": "SKU00055",
        "product_name": "Conserves Inviter",
        "quantity": 1
      }
    ]
  },
  {
    "order_id": "ORD-2026-01-12-S05-0004",
    "store_id": "STORE05",
    "order_date": "2026-01-12",
    "order_time": "12:38:33",
    "customer_id": "6b358d15-590c-4e67-8d1b-6d80c8575c8a",
    "items": [
      {
        "sku": "SKU00041",
        "product_name": "Crème Chair",
        "quantity": 2
      },
      {
        "sku": "SKU00005",
        "product_name": "Porc Étonner",
        "quantity": 3
      },
      {
        "sku": "SKU00025",
        "product_name": "Conserves Problème",
        "quantity": 2
      },
      {
        "sku": "SKU00043",
        "product_name": "Nettoyant Occasion",
        "quantity": 5
      },
      {
        "sku": "SKU00006",
        "product_name": "Huile Enfin",
        "quantity": 5
      },
      {
        "sku": "SKU00042",
        "product_name": "Confiture Toit",
        "quantity": 3
      }
    ]
  },
  {
    "order_id": "ORD-2026-01-12-S05-0005",
    "store_id": "STORE05",
    "order_date": "2026-01-12",
    "order_time": "20:03:44",
    "customer_id": "31208bde-3c52-468a-8ec6-1be5012b809e",
    "items": [
      {
        "sku": "SKU00054",
        "product_name": "Sel Moins",
        "quantity": 2
      },
      {
        "sku": "SKU00027",
        "product_name": "Poisson pané Flot",
        "quantity": 1
      },
      {
        "sku": "SKU00077",
        "product_name": "Nettoyant Éprouver",
        "quantity": 4
      },
      {
        "sku": "SKU00095",
        "product_name": "Boeuf Toucher",
        "quantity": 5
      }
    ]
  },
  {
    "order_id": "ORD-2026-01-12-S05-0006",
    "store_id": "STORE05",
    "order_date": "2026-01-12",
    "order_time": "14:30:32",
    "customer_id": "fa0f01a4-87bb-4f6d-bc92-0c731e14fe04",
    "items": [
      {
        "sku": "SKU00097",
        "product_name": "Huile Curiosité",
        "quantity": 1
      },
      {
        "sku": "SKU00015",
        "product_name": "Crème Accuser",
        "quantity": 4
      }
    ]
  },
  {
    "order_id": "ORD-2026-01-12-S05-0007",
    "store_id": "STORE05",
    "order_date": "2026-01-12",
    "order_time": "18:17:42",
    "customer_id": "dcdbf14e-5ca5-4057-9e71-9a56187ebca4",
    "items": [
      {
        "sku": "SKU00007",
        "product_name": "Jus Beau",
        "quantity": 2
      },
      {
        "sku": "SKU00005",
        "product_name": "Porc Étonner",
        "quantity": 1
      },
      {
        "sku": "SKU00063",
        "product_name": "Thé Nommer",
        "quantity": 3
      },
      {
        "sku": "SKU00034",
        "product_name": "Eau Rien",
        "quantity": 5
      },
      {
        "sku": "SKU00025",
        "product_name": "Conserves Problème",
        "quantity": 5
      },
      {
        "sku": "SKU00083",
        "product_name": "Miel Mode",
        "quantity": 1
      },
      {
        "sku": "SKU00023",
        "product_name": "Pâtes Inconnu",
        "quantity": 1
      }
    ]
  },
  {
    "order_id": "ORD-2026-01-12-S05-0008",
    "store_id": "STORE05",
    "order_date": "2026-01-12",
    "order_time": "18:54:16",
    "customer_id": "81ee30e4-8a2b-466e-bc9d-c0d0c2d94cc9",
    "items": [
      {
        "sku": "SKU00085",
        "product_name": "Biscuits Défendre",
        "quantity": 5
      },
      {
        "sku": "SKU00035",
        "product_name": "Biscuits Peur",
        "quantity": 2
      },
      {
        "sku": "SKU00090",
        "product_name": "Laitue Parvenir",
        "quantity": 5
      },
      {
        "sku": "SKU00017",
        "product_name": "Soda Vol",
        "quantity": 1
      },
      {
        "sku": "SKU00055",
        "product_name": "Conserves Inviter",
        "quantity": 3
      },
      {
        "sku": "SKU00020",
        "product_name": "Riz Ensuite",
        "quantity": 1
      },
      {
        "sku": "SKU00094",
        "product_name": "Poisson pané Rencontrer",
        "quantity": 2
      }
    ]
  },
  {
    "order_id": "ORD-2026-01-12-S05-0009",
    "store_id": "STORE05",
    "order_date": "2026-01-12",
    "order_time": "20:02:07",
    "customer_id": "a05ff5e6-c534-4e41-b6d6-dc3938227b0d",
    "items": [
      {
        "sku": "SKU00055",
        "product_name": "Conserves Inviter",
        "quantity": 4
      },
      {
        "sku": "SKU00063",
        "product_name": "Thé Nommer",
        "quantity": 1
      },
      {
        "sku": "SKU00062",
        "product_name": "Huile Côté",
        "quantity": 5
      },
      {
        "sku": "SKU00041",
        "product_name": "Crème Chair",
        "quantity": 2
      },
      {
        "sku": "SKU00100",
        "product_name": "Sucre Émotion",
        "quantity": 4
      },
      {
        "sku": "SKU00040",
        "product_name": "Biscuits Cerveau",
        "quantity": 3
      },
      {
        "sku": "SKU00083",
        "product_name": "Miel Mode",
        "quantity": 1
      },
      {
        "sku": "SKU00088",
        "product_name": "Yaourt Mémoire",
        "quantity": 4
      }
    ]
  },
  {
    "order_id": "ORD-2026-01-12-S05-0010",
    "store_id": "STORE05",
    "order_date": "2026-01-12",
    "order_time": "11:01:32",
    "customer_id": "0d95ee72-46c3-4497-b546-9cb1a8c9aa31",
    "items": [
      {
        "sku": "SKU00021",
        "product_name": "Bananes Bien",
        "quantity": 5
      }
    ]
  },
  {
    "order_id": "ORD-2026-01-12-S05-0011",
    "store_id": "STORE05",
    "order_date": "2026-01-12",
    "order_time": "16:40:57",
    "customer_id": "26331cc6-cbee-43e3-9cd8-89e231979167",
    "items": [
      {
        "sku": "SKU00073",
        "product_name": "Yaourt Tenir",
        "quantity": 1
      }
    ]
  },
  {
    "order_id": "ORD-2026-01-12-S05-0012",
    "store_id": "STORE05",
    "order_date": "2026-01-12",
    "order_time": "10:25:09",
    "customer_id": "e9570a2a-f7f4-4477-9802-13baaf6c2278",
    "items": [
      {
        "sku": "SKU00056",
        "product_name": "Lait infantile Chien",
        "quantity": 5
      },
      {
        "sku": "SKU00044",
        "product_name": "Bananes Lentement",
        "quantity": 2
      },
      {
        "sku": "SKU00001",
        "product_name": "Boeuf Oreille",
        "quantity": 5
      },
      {
        "sku": "SKU00062",
        "product_name": "Huile Côté",
        "quantity": 4
      },
      {
        "sku": "SKU00032",
        "product_name": "Conserves Conscience",
        "quantity": 5
      },
      {
        "sku": "SKU00043",
        "product_name": "Nettoyant Occasion",
        "quantity": 2
      },
      {
        "sku": "SKU00066",
        "product_name": "Soda Peau",
        "quantity": 3
      },
      {
        "sku": "SKU00060",
        "product_name": "Savon Ramasser",
        "quantity": 3
      }
    ]
  },
  {
    "order_id": "ORD-2026-01-12-S05-0013",
    "store_id": "STORE05",
    "order_date": "2026-01-12",
    "order_time": "13:48:01",
    "customer_id": "28e60130-2d23-4ed1-bf5d-21f279731ea8",
    "items": [
      {
        "sku": "SKU00090",
        "product_name": "Laitue Parvenir",
        "quantity": 1
      },
      {
        "sku": "SKU00065",
        "product_name": "Poisson pané Flot",
        "quantity": 4
      },
      {
        "sku": "SKU00022",
        "product_name": "Savon Approcher",
        "quantity": 2
      },
      {
        "sku": "SKU00054",
        "product_name": "Sel Moins",
        "quantity": 5
      },
      {
        "sku": "SKU00013",
        "product_name": "Petits pots Saison",
        "quantity": 5
      },
      {
        "sku": "SKU00007",
        "product_name": "Jus Beau",
        "quantity": 5
      },
      {
        "sku": "SKU00017",
        "product_name": "Soda Vol",
        "quantity": 3
      },
      {
        "sku": "SKU00080",
        "product_name": "Confiture Poids",
        "quantity": 5
      },
      {
        "sku": "SKU00018",
        "product_name": "Liquide vaisselle Sourire",
        "quantity": 2
      }
    ]
  },
  {
    "order_id": "ORD-2026-01-12-S05-0014",
    "store_id": "STORE05",
    "order_date": "2026-01-12",
    "order_time": "18:17:05",
    "customer_id": "0dd4c0e6-0b09-4fcc-ac34-4cf0ab8e77a1",
    "items": [
      {
        "sku": "SKU00096",
        "product_name": "Lessive Point",
        "quantity": 1
      },
      {
        "sku": "SKU00028",
        "product_name": "Carottes Tranquille",
        "quantity": 4
      },
      {
        "sku": "SKU00046",
        "product_name": "Biscuits Moyen",
        "quantity": 5
      },
      {
        "sku": "SKU00006",
        "product_name": "Huile Enfin",
        "quantity": 1
      },
      {
        "sku": "SKU00012",
        "product_name": "Boeuf Entourer",
        "quantity": 4
      },
      {
        "sku": "SKU00083",
        "product_name": "Miel Mode",
        "quantity": 5
      },
      {
        "sku": "SKU00078",
        "product_name": "Thon Dehors",
        "quantity": 1
      },
      {
        "sku": "SKU00008",
        "product_name": "Riz Inutile",
        "quantity": 5
      }
    ]
  },
  {
    "order_id": "ORD-2026-01-12-S05-0015",
    "store_id": "STORE05",
    "order_date": "2026-01-12",
    "order_time": "21:07:10",
    "customer_id": "35a7ac9b-48f9-4d0d-9d3b-c1d3a5159982",
    "items": [
      {
        "sku": "SKU00054",
        "product_name": "Sel Moins",
        "quantity": 4
      },
      {
        "sku": "SKU00055",
        "product_name": "Conserves Inviter",
        "quantity": 4
      },
      {
        "sku": "SKU00040",
        "product_name": "Biscuits Cerveau",
        "quantity": 4
      },
      {
        "sku": "SKU00072",
        "product_name": "Crevettes Autorité",
        "quantity": 2
      },
      {
        "sku": "SKU00012",
        "product_name": "Boeuf Entourer",
        "quantity": 1
      },
      {
        "sku": "SKU00062",
        "product_name": "Huile Côté",
        "quantity": 5
      },
      {
        "sku": "SKU00042",
        "product_name": "Confiture Toit",
        "quantity": 1
      }
    ]
  },
  {
    "order_id": "ORD-2026-01-12-S05-0016",
    "store_id": "STORE05",
    "order_date": "2026-01-12",
    "order_time": "10:53:01",
    "customer_id": "9de7df7b-5594-452b-805a-8e7e6f46a41f",
    "items": [
      {
        "sku": "SKU00066",
        "product_name": "Soda Peau",
        "quantity": 2
      },
      {
        "sku": "SKU00019",
        "product_name": "Liquide vaisselle Baisser",
        "quantity": 5
      },
      {
        "sku": "SKU00015",
        "product_name": "Crème Accuser",
        "quantity": 1
      },
      {
        "sku": "SKU00096",
        "product_name": "Lessive Point",
        "quantity": 4
      },
      {
        "sku": "SKU00067",
        "product_name": "Céréales Étranger",
        "quantity": 1
      },
      {
        "sku": "SKU00057",
        "product_name": "Lait Étrange",
        "quantity": 2
      },
      {
        "sku": "SKU00049",
        "product_name": "Légumes surgelés Trésor",
        "quantity": 4
      },
      {
        "sku": "SKU00033",
        "product_name": "Sauce tomate Réunir",
        "quantity": 2
      },
      {
        "sku": "SKU00040",
        "product_name": "Biscuits Cerveau",
        "quantity": 3
      }
    ]
  },
  {
    "order_id": "ORD-2026-01-12-S05-0017",
    "store_id": "STORE05",
    "order_date": "2026-01-12",
    "order_time": "12:13:20",
    "customer_id": "74017bb3-c227-4738-a3dc-419dce1e8d1f",
    "items": [
      {
        "sku": "SKU00031",
        "product_name": "Porc Rapport",
        "quantity": 5
      },
      {
        "sku": "SKU00082",
        "product_name": "Beurre Également",
        "quantity": 4
      },
      {
        "sku": "SKU00061",
        "product_name": "Savon Parent",
        "quantity": 2
      },
      {
        "sku": "SKU00060",
        "product_name": "Savon Ramasser",
        "quantity": 3
      },
      {
        "sku": "SKU00081",
        "product_name": "Crème Pleurer",
        "quantity": 3
      }
    ]
  },
  {
    "order_id": "ORD-2026-01-12-S05-0018",
    "store_id": "STORE05",
    "order_date": "2026-01-12",
    "order_time": "18:52:56",
    "customer_id": "0d6dcb42-bd8b-4603-9abb-574e0b16dac4",
    "items": [
      {
        "sku": "SKU00007",
        "product_name": "Jus Beau",
        "quantity": 4
      },
      {
        "sku": "SKU00037",
        "product_name": "Chocolat Peur",
        "quantity": 1
      },
      {
        "sku": "SKU00047",
        "product_name": "Saumon Perdu",
        "quantity": 1
      },
      {
        "sku": "SKU00049",
        "product_name": "Légumes surgelés Trésor",
        "quantity": 2
      },
      {
        "sku": "SKU00028",
        "product_name": "Carottes Tranquille",
        "quantity": 1
      },
      {
        "sku": "SKU00055",
        "product_name": "Conserves Inviter",
        "quantity": 3
      },
      {
        "sku": "SKU00069",
        "product_name": "Glace Pain",
        "quantity": 2
      },
      {
        "sku": "SKU00096",
        "product_name": "Lessive Point",
        "quantity": 3
      },
      {
        "sku": "SKU00078",
        "product_name": "Thon Dehors",
        "quantity": 2
      }
    ]
  },
  {
    "order_id": "ORD-2026-01-12-S05-0019",
    "store_id": "STORE05",
    "order_date": "2026-01-12",
    "order_time": "11:26:38",
    "customer_id": "2875ad5d-2d06-4862-8990-779cecc3b699",
    "items": [
      {
        "sku": "SKU00024",
        "product_name": "Oranges Boire",
        "quantity": 1
      },
      {
        "sku": "SKU00095",
        "product_name": "Boeuf Toucher",
        "quantity": 5
      },
      {
        "sku": "SKU00019",
        "product_name": "Liquide vaisselle Baisser",
        "quantity": 1
      },
      {
        "sku": "SKU00078",
        "product_name": "Thon Dehors",
        "quantity": 2
      },
      {
        "sku": "SKU00088",
        "product_name": "Yaourt Mémoire",
        "quantity": 2
      },
      {
        "sku": "SKU00047",
        "product_name": "Saumon Perdu",
        "quantity": 4
      }
    ]
  },
  {
    "order_id": "ORD-2026-01-12-S05-0020",
    "store_id": "STORE05",
    "order_date": "2026-01-12",
    "order_time": "11:00:11",
    "customer_id": "83d0bae7-7c2c-4bcf-8770-d18fc9160147",
    "items": [
      {
        "sku": "SKU00098",
        "product_name": "Lingettes Discuter",
        "quantity": 5
      },
      {
        "sku": "SKU00018",
        "product_name": "Liquide vaisselle Sourire",
        "quantity": 3
      },
      {
        "sku": "SKU00062",
        "product_name": "Huile Côté",
        "quantity": 5
      },
      {
        "sku": "SKU00099",
        "product_name": "Poulet Gauche",
        "quantity": 4
      },
      {
        "sku": "SKU00036",
        "product_name": "Crème Étage",
        "quantity": 4
      },
      {
        "sku": "SKU00076",
        "product_name": "Lingettes Certainement",
        "quantity": 1
      }
    ]
  },
  {
    "order_id": "ORD-2026-01-12-S05-0021",
    "store_id": "STORE05",
    "order_date": "2026-01-12",
    "order_time": "17:24:41",
    "customer_id": "3c3c9c08-e523-48a9-9223-d9061db67101",
    "items": [
      {
        "sku": "SKU00006",
        "product_name": "Huile Enfin",
        "quantity": 4
      },
      {
        "sku": "SKU00016",
        "product_name": "Crème Boire",
        "quantity": 1
      },
      {
        "sku": "SKU00024",
        "product_name": "Oranges Boire",
        "quantity": 2
      },
      {
        "sku": "SKU00047",
        "product_name": "Saumon Perdu",
        "quantity": 3
      }
    ]
  },
  {
    "order_id": "ORD-2026-01-12-S05-0022",
    "store_id": "STORE05",
    "order_date": "2026-01-12",
    "order_time": "14:20:08",
    "customer_id": "946b4482-97bb-4fbf-b1df-c82cb8addf54",
    "items": [
      {
        "sku": "SKU00079",
        "product_name": "Éponges Monter",
        "quantity": 3
      },
      {
        "sku": "SKU00046",
        "product_name": "Biscuits Moyen",
        "quantity": 1
      },
      {
        "sku": "SKU00078",
        "product_name": "Thon Dehors",
        "quantity": 3
      },
      {
        "sku": "SKU00051",
        "product_name": "Thé Tant",
        "quantity": 3
      }
    ]
  },
  {
    "order_id": "ORD-2026-01-12-S05-0023",
    "store_id": "STORE05",
    "order_date": "2026-01-12",
    "order_time": "19:48:27",
    "customer_id": "bf4113cb-32e1-4f17-ab47-ed615372ebed",
    "items": [
      {
        "sku": "SKU00099",
        "product_name": "Poulet Gauche",
        "quantity": 3
      },
      {
        "sku": "SKU00093",
        "product_name": "Lait infantile Vif",
        "quantity": 5
      },
      {
        "sku": "SKU00086",
        "product_name": "Éponges Manier",
        "quantity": 1
      },
      {
        "sku": "SKU00064",
        "product_name": "Pâtes Deviner",
        "quantity": 5
      }
    ]
  },
  {
    "order_id": "ORD-2026-01-12-S05-0024",
    "store_id": "STORE05",
    "order_date": "2026-01-12",
    "order_time": "20:23:49",
    "customer_id": "3ae56c8d-5360-46e7-a5fb-c1c0ad463549",
    "items": [
      {
        "sku": "SKU00057",
        "product_name": "Lait Étrange",
        "quantity": 3
      },
      {
        "sku": "SKU00017",
        "product_name": "Soda Vol",
        "quantity": 1
      },
      {
        "sku": "SKU00003",
        "product_name": "Biscuits Part",
        "quantity": 2
      },
      {
        "sku": "SKU00091",
        "product_name": "Lait infantile Fortune",
        "quantity": 4
      },
      {
        "sku": "SKU00073",
        "product_name": "Yaourt Tenir",
        "quantity": 3
      },
      {
        "sku": "SKU00078",
        "product_name": "Thon Dehors",
        "quantity": 5
      },
      {
        "sku": "SKU00056",
        "product_name": "Lait infantile Chien",
        "quantity": 5
      },
      {
        "sku": "SKU00046",
        "product_name": "Biscuits Moyen",
        "quantity": 2
      }
    ]
  },
  {
    "order_id": "ORD-2026-01-12-S05-0025",
    "store_id": "STORE05",
    "order_date": "2026-01-12",
    "order_time": "13:55:45",
    "customer_id": "3a4fece7-537d-46c6-9c31-aaf3c76aec88",
    "items": [
      {
        "sku": "SKU00013",
        "product_name": "Petits pots Saison",
        "quantity": 5
      },
      {
        "sku": "SKU00070",
        "product_name": "Dentifrice Rejoindre",
        "quantity": 4
      }
    ]
  },
  {
    "order_id": "ORD-2026-01-12-S05-0026",
    "store_id": "STORE05",
    "order_date": "2026-01-12",
    "order_time": "11:33:23",
    "customer_id": "699fdb02-bcdd-4b48-bcb3-c9fa191abb3d",
    "items": [
      {
        "sku": "SKU00008",
        "product_name": "Riz Inutile",
        "quantity": 3
      },
      {
        "sku": "SKU00091",
        "product_name": "Lait infantile Fortune",
        "quantity": 4
      },
      {
        "sku": "SKU00041",
        "product_name": "Crème Chair",
        "quantity": 4
      },
      {
        "sku": "SKU00087",
        "product_name": "Confiture Absence",
        "quantity": 2
      },
      {
        "sku": "SKU00071",
        "product_name": "Thon Chaleur",
        "quantity": 2
      },
      {
        "sku": "SKU00011",
        "product_name": "Frites Remonter",
        "quantity": 2
      },
      {
        "sku": "SKU00066",
        "product_name": "Soda Peau",
        "quantity": 2
      },
      {
        "sku": "SKU00019",
        "product_name": "Liquide vaisselle Baisser",
        "quantity": 4
      }
    ]
  },
  {
    "order_id": "ORD-2026-01-12-S05-0027",
    "store_id": "STORE05",
    "order_date": "2026-01-12",
    "order_time": "14:25:51",
    "customer_id": "e43081aa-6022-43ff-b330-4e33deb0de7d",
    "items": [
      {
        "sku": "SKU00070",
        "product_name": "Dentifrice Rejoindre",
        "quantity": 4
      }
    ]
  },
  {
    "order_id": "ORD-2026-01-12-S05-0028",
    "store_id": "STORE05",
    "order_date": "2026-01-12",
    "order_time": "20:39:33",
    "customer_id": "95c89b2d-7892-4145-92d2-d7e6387d5add",
    "items": [
      {
        "sku": "SKU00020",
        "product_name": "Riz Ensuite",
        "quantity": 4
      },
      {
        "sku": "SKU00002",
        "product_name": "Crème Projet",
        "quantity": 3
      },
      {
        "sku": "SKU00024",
        "product_name": "Oranges Boire",
        "quantity": 5
      },
      {
        "sku": "SKU00060",
        "product_name": "Savon Ramasser",
        "quantity": 1
      },
      {
        "sku": "SKU00091",
        "product_name": "Lait infantile Fortune",
        "quantity": 2
      },
      {
        "sku": "SKU00035",
        "product_name": "Biscuits Peur",
        "quantity": 3
      },
      {
        "sku": "SKU00023",
        "product_name": "Pâtes Inconnu",
        "quantity": 5
      },
      {
        "sku": "SKU00086",
        "product_name": "Éponges Manier",
        "quantity": 3
      },
      {
        "sku": "SKU00075",
        "product_name": "Couches Aide",
        "quantity": 5
      },
      {
        "sku": "SKU00005",
        "product_name": "Porc Étonner",
        "quantity": 4
      }
    ]
  },
  {
    "order_id": "ORD-2026-01-12-S05-0029",
    "store_id": "STORE05",
    "order_date": "2026-01-12",
    "order_time": "10:47:03",
    "customer_id": "6f94da50-e3f7-43a7-8de9-2f1b7c0224e5",
    "items": [
      {
        "sku": "SKU00035",
        "product_name": "Biscuits Peur",
        "quantity": 3
      },
      {
        "sku": "SKU00002",
        "product_name": "Crème Projet",
        "quantity": 2
      },
      {
        "sku": "SKU00040",
        "product_name": "Biscuits Cerveau",
        "quantity": 5
      }
    ]
  },
  {
    "order_id": "ORD-2026-01-12-S05-0030",
    "store_id": "STORE05",
    "order_date": "2026-01-12",
    "order_time": "14:11:10",
    "customer_id": "9c03d65c-ed8a-428c-b756-999b251adf0e",
    "items": [
      {
        "sku": "SKU00100",
        "product_name": "Sucre Émotion",
        "quantity": 4
      },
      {
        "sku": "SKU00063",
        "product_name": "Thé Nommer",
        "quantity": 5
      },
      {
        "sku": "SKU00010",
        "product_name": "Déodorant Saisir",
        "quantity": 5
      },
      {
        "sku": "SKU00071",
        "product_name": "Thon Chaleur",
        "quantity": 2
      },
      {
        "sku": "SKU00090",
        "product_name": "Laitue Parvenir",
        "quantity": 1
      },
      {
        "sku": "SKU00099",
        "product_name": "Poulet Gauche",
        "quantity": 4
      },
      {
        "sku": "SKU00057",
        "product_name": "Lait Étrange",
        "quantity": 4
      },
      {
        "sku": "SKU00014",
        "product_name": "Eau En",
        "quantity": 4
      },
      {
        "sku": "SKU00058",
        "product_name": "Lingettes Distinguer",
        "quantity": 1
      }
    ]
  },
  {
    "order_id": "ORD-2026-01-12-S05-0031",
    "store_id": "STORE05",
    "order_date": "2026-01-12",
    "order_time": "17:37:26",
    "customer_id": "5f9cb7e0-6328-443e-ad95-63ed747a4829",
    "items": [
      {
        "sku": "SKU00021",
        "product_name": "Bananes Bien",
        "quantity": 2
      },
      {
        "sku": "SKU00049",
        "product_name": "Légumes surgelés Trésor",
        "quantity": 2
      },
      {
        "sku": "SKU00044",
        "product_name": "Bananes Lentement",
        "quantity": 3
      },
      {
        "sku": "SKU00011",
        "product_name": "Frites Remonter",
        "quantity": 4
      },
      {
        "sku": "SKU00087",
        "product_name": "Confiture Absence",
        "quantity": 5
      },
      {
        "sku": "SKU00048",
        "product_name": "Biscuits Avancer",
        "quantity": 5
      },
      {
        "sku": "SKU00082",
        "product_name": "Beurre Également",
        "quantity": 5
      },
      {
        "sku": "SKU00077",
        "product_name": "Nettoyant Éprouver",
        "quantity": 2
      }
    ]
  },
  {
    "order_id": "ORD-2026-01-12-S05-0032",
    "store_id": "STORE05",
    "order_date": "2026-01-12",
    "order_time": "19:38:50",
    "customer_id": "31b42308-b846-4413-b52e-761322eb69b1",
    "items": [
      {
        "sku": "SKU00098",
        "product_name": "Lingettes Discuter",
        "quantity": 5
      },
      {
        "sku": "SKU00028",
        "product_name": "Carottes Tranquille",
        "quantity": 2
      },
      {
        "sku": "SKU00020",
        "product_name": "Riz Ensuite",
        "quantity": 2
      },
      {
        "sku": "SKU00054",
        "product_name": "Sel Moins",
        "quantity": 3
      },
      {
        "sku": "SKU00083",
        "product_name": "Miel Mode",
        "quantity": 5
      },
      {
        "sku": "SKU00088",
        "product_name": "Yaourt Mémoire",
        "quantity": 4
      },
      {
        "sku": "SKU00097",
        "product_name": "Huile Curiosité",
        "quantity": 4
      },
      {
        "sku": "SKU00003",
        "product_name": "Biscuits Part",
        "quantity": 5
      },
      {
        "sku": "SKU00033",
        "product_name": "Sauce tomate Réunir",
        "quantity": 5
      },
      {
        "sku": "SKU00046",
        "product_name": "Biscuits Moyen",
        "quantity": 4
      }
    ]
  },
  {
    "order_id": "ORD-2026-01-12-S05-0033",
    "store_id": "STORE05",
    "order_date": "2026-01-12",
    "order_time": "15:39:11",
    "customer_id": "450ab36d-f9be-47f3-9bcc-90fca1cc22d8",
    "items": [
      {
        "sku": "SKU00004",
        "product_name": "Saumon Comme",
        "quantity": 3
      },
      {
        "sku": "SKU00005",
        "product_name": "Porc Étonner",
        "quantity": 4
      },
      {
        "sku": "SKU00078",
        "product_name": "Thon Dehors",
        "quantity": 1
      },
      {
        "sku": "SKU00051",
        "product_name": "Thé Tant",
        "quantity": 3
      },
      {
        "sku": "SKU00097",
        "product_name": "Huile Curiosité",
        "quantity": 1
      },
      {
        "sku": "SKU00093",
        "product_name": "Lait infantile Vif",
        "quantity": 2
      },
      {
        "sku": "SKU00082",
        "product_name": "Beurre Également",
        "quantity": 3
      },
      {
        "sku": "SKU00021",
        "product_name": "Bananes Bien",
        "quantity": 5
      }
    ]
  },
  {
    "order_id": "ORD-2026-01-12-S05-0034",
    "store_id": "STORE05",
    "order_date": "2026-01-12",
    "order_time": "8:33:55",
    "customer_id": "083759f8-2090-435e-95fc-f99133c417d5",
    "items": [
      {
        "sku": "SKU00063",
        "product_name": "Thé Nommer",
        "quantity": 3
      },
      {
        "sku": "SKU00040",
        "product_name": "Biscuits Cerveau",
        "quantity": 5
      },
      {
        "sku": "SKU00064",
        "product_name": "Pâtes Deviner",
        "quantity": 2
      }
    ]
  },
  {
    "order_id": "ORD-2026-01-12-S05-0035",
    "store_id": "STORE05",
    "order_date": "2026-01-12",
    "order_time": "13:12:38",
    "customer_id": "47d5ac92-0f45-45da-9194-1591b134b58f",
    "items": [
      {
        "sku": "SKU00024",
        "product_name": "Oranges Boire",
        "quantity": 5
      },
      {
        "sku": "SKU00017",
        "product_name": "Soda Vol",
        "quantity": 2
      }
    ]
  },
  {
    "order_id": "ORD-2026-01-12-S05-0036",
    "store_id": "STORE05",
    "order_date": "2026-01-12",
    "order_time": "9:09:08",
    "customer_id": "772d416d-da05-42fc-9c71-a82122f1c32b",
    "items": [
      {
        "sku": "SKU00064",
        "product_name": "Pâtes Deviner",
        "quantity": 4
      },
      {
        "sku": "SKU00036",
        "product_name": "Crème Étage",
        "quantity": 1
      },
      {
        "sku": "SKU00094",
        "product_name": "Poisson pané Rencontrer",
        "quantity": 1
      },
      {
        "sku": "SKU00087",
        "product_name": "Confiture Absence",
        "quantity": 1
      },
      {
        "sku": "SKU00085",
        "product_name": "Biscuits Défendre",
        "quantity": 1
      },
      {
        "sku": "SKU00065",
        "product_name": "Poisson pané Flot",
        "quantity": 3
      },
      {
        "sku": "SKU00083",
        "product_name": "Miel Mode",
        "quantity": 3
      },
      {
        "sku": "SKU00010",
        "product_name": "Déodorant Saisir",
        "quantity": 1
      },
      {
        "sku": "SKU00022",
        "product_name": "Savon Approcher",
        "quantity": 4
      },
      {
        "sku": "SKU00015",
        "product_name": "Crème Accuser",
        "quantity": 4
      }
    ]
  },
  {
    "order_id": "ORD-2026-01-12-S05-0037",
    "store_id": "STORE05",
    "order_date": "2026-01-12",
    "order_time": "21:39:46",
    "customer_id": "c2a59d7b-2bd3-4971-ab10-b78675656daf",
    "items": [
      {
        "sku": "SKU00007",
        "product_name": "Jus Beau",
        "quantity": 1
      },
      {
        "sku": "SKU00055",
        "product_name": "Conserves Inviter",
        "quantity": 3
      },
      {
        "sku": "SKU00031",
        "product_name": "Porc Rapport",
        "quantity": 2
      }
    ]
  },
  {
    "order_id": "ORD-2026-01-12-S05-0038",
    "store_id": "STORE05",
    "order_date": "2026-01-12",
    "order_time": "21:18:46",
    "customer_id": "4b8fb475-e2eb-42d2-b848-52b657f498e0",
    "items": [
      {
        "sku": "SKU00008",
        "product_name": "Riz Inutile",
        "quantity": 5
      }
    ]
  },
  {
    "order_id": "ORD-2026-01-12-S05-0039",
    "store_id": "STORE05",
    "order_date": "2026-01-12",
    "order_time": "11:19:07",
    "customer_id": "cb68a34e-ca1f-4ff2-a823-442c9a87e357",
    "items": [
      {
        "sku": "SKU00063",
        "product_name": "Thé Nommer",
        "quantity": 1
      },
      {
        "sku": "SKU00053",
        "product_name": "Glace Bas",
        "quantity": 2
      }
    ]
  },
  {
    "order_id": "ORD-2026-01-12-S05-0040",
    "store_id": "STORE05",
    "order_date": "2026-01-12",
    "order_time": "20:36:31",
    "customer_id": "e7d3f770-9c8d-4ade-b3e8-16b5a353ea98",
    "items": [
      {
        "sku": "SKU00094",
        "product_name": "Poisson pané Rencontrer",
        "quantity": 3
      },
      {
        "sku": "SKU00014",
        "product_name": "Eau En",
        "quantity": 2
      },
      {
        "sku": "SKU00033",
        "product_name": "Sauce tomate Réunir",
        "quantity": 5
      },
      {
        "sku": "SKU00027",
        "product_name": "Poisson pané Flot",
        "quantity": 4
      },
      {
        "sku": "SKU00023",
        "product_name": "Pâtes Inconnu",
        "quantity": 2
      },
      {
        "sku": "SKU00078",
        "product_name": "Thon Dehors",
        "quantity": 1
      },
      {
        "sku": "SKU00090",
        "product_name": "Laitue Parvenir",
        "quantity": 5
      },
      {
        "sku": "SKU00025",
        "product_name": "Conserves Problème",
        "quantity": 5
      },
      {
        "sku": "SKU00028",
        "product_name": "Carottes Tranquille",
        "quantity": 5
      }
    ]
  },
  {
    "order_id": "ORD-2026-01-12-S05-0041",
    "store_id": "STORE05",
    "order_date": "2026-01-12",
    "order_time": "18:20:53",
    "customer_id": "8d8164b0-f85a-4287-93ff-c45f2b80e44a",
    "items": [
      {
        "sku": "SKU00061",
        "product_name": "Savon Parent",
        "quantity": 4
      },
      {
        "sku": "SKU00056",
        "product_name": "Lait infantile Chien",
        "quantity": 3
      },
      {
        "sku": "SKU00010",
        "product_name": "Déodorant Saisir",
        "quantity": 2
      },
      {
        "sku": "SKU00031",
        "product_name": "Porc Rapport",
        "quantity": 2
      },
      {
        "sku": "SKU00093",
        "product_name": "Lait infantile Vif",
        "quantity": 3
      },
      {
        "sku": "SKU00092",
        "product_name": "Shampoing Nord",
        "quantity": 1
      },
      {
        "sku": "SKU00053",
        "product_name": "Glace Bas",
        "quantity": 3
      }
    ]
  },
  {
    "order_id": "ORD-2026-01-12-S05-0042",
    "store_id": "STORE05",
    "order_date": "2026-01-12",
    "order_time": "19:41:09",
    "customer_id": "6964eb16-1623-4e87-bacd-c514dae18b28",
    "items": [
      {
        "sku": "SKU00012",
        "product_name": "Boeuf Entourer",
        "quantity": 1
      },
      {
        "sku": "SKU00093",
        "product_name": "Lait infantile Vif",
        "quantity": 5
      },
      {
        "sku": "SKU00001",
        "product_name": "Boeuf Oreille",
        "quantity": 2
      },
      {
        "sku": "SKU00063",
        "product_name": "Thé Nommer",
        "quantity": 2
      },
      {
        "sku": "SKU00084",
        "product_name": "Crème Baisser",
        "quantity": 3
      },
      {
        "sku": "SKU00058",
        "product_name": "Lingettes Distinguer",
        "quantity": 2
      },
      {
        "sku": "SKU00055",
        "product_name": "Conserves Inviter",
        "quantity": 1
      },
      {
        "sku": "SKU00099",
        "product_name": "Poulet Gauche",
        "quantity": 5
      },
      {
        "sku": "SKU00091",
        "product_name": "Lait infantile Fortune",
        "quantity": 4
      },
      {
        "sku": "SKU00021",
        "product_name": "Bananes Bien",
        "quantity": 4
      }
    ]
  },
  {
    "order_id": "ORD-2026-01-12-S05-0043",
    "store_id": "STORE05",
    "order_date": "2026-01-12",
    "order_time": "17:51:06",
    "customer_id": "dcb913b4-7d3d-46ca-8592-a38fdb62a1f7",
    "items": [
      {
        "sku": "SKU00065",
        "product_name": "Poisson pané Flot",
        "quantity": 5
      },
      {
        "sku": "SKU00093",
        "product_name": "Lait infantile Vif",
        "quantity": 3
      },
      {
        "sku": "SKU00095",
        "product_name": "Boeuf Toucher",
        "quantity": 5
      },
      {
        "sku": "SKU00012",
        "product_name": "Boeuf Entourer",
        "quantity": 5
      },
      {
        "sku": "SKU00008",
        "product_name": "Riz Inutile",
        "quantity": 4
      },
      {
        "sku": "SKU00089",
        "product_name": "Biscuits Faute",
        "quantity": 2
      },
      {
        "sku": "SKU00076",
        "product_name": "Lingettes Certainement",
        "quantity": 5
      }
    ]
  },
  {
    "order_id": "ORD-2026-01-12-S05-0044",
    "store_id": "STORE05",
    "order_date": "2026-01-12",
    "order_time": "21:02:41",
    "customer_id": "7936931e-9771-480b-b768-c85bfee3dbaa",
    "items": [
      {
        "sku": "SKU00005",
        "product_name": "Porc Étonner",
        "quantity": 3
      },
      {
        "sku": "SKU00002",
        "product_name": "Crème Projet",
        "quantity": 4
      },
      {
        "sku": "SKU00021",
        "product_name": "Bananes Bien",
        "quantity": 5
      },
      {
        "sku": "SKU00061",
        "product_name": "Savon Parent",
        "quantity": 2
      },
      {
        "sku": "SKU00096",
        "product_name": "Lessive Point",
        "quantity": 1
      },
      {
        "sku": "SKU00012",
        "product_name": "Boeuf Entourer",
        "quantity": 1
      },
      {
        "sku": "SKU00086",
        "product_name": "Éponges Manier",
        "quantity": 4
      },
      {
        "sku": "SKU00079",
        "product_name": "Éponges Monter",
        "quantity": 3
      },
      {
        "sku": "SKU00069",
        "product_name": "Glace Pain",
        "quantity": 2
      }
    ]
  },
  {
    "order_id": "ORD-2026-01-12-S05-0045",
    "store_id": "STORE05",
    "order_date": "2026-01-12",
    "order_time": "15:39:26",
    "customer_id": "03b68657-4777-4e21-b677-a166d644e9ae",
    "items": [
      {
        "sku": "SKU00034",
        "product_name": "Eau Rien",
        "quantity": 4
      }
    ]
  },
  {
    "order_id": "ORD-2026-01-12-S05-0046",
    "store_id": "STORE05",
    "order_date": "2026-01-12",
    "order_time": "16:27:36",
    "customer_id": "df629d0c-bc76-47a0-ad98-a416bae27198",
    "items": [
      {
        "sku": "SKU00088",
        "product_name": "Yaourt Mémoire",
        "quantity": 3
      },
      {
        "sku": "SKU00003",
        "product_name": "Biscuits Part",
        "quantity": 4
      }
    ]
  },
  {
    "order_id": "ORD-2026-01-12-S05-0047",
    "store_id": "STORE05",
    "order_date": "2026-01-12",
    "order_time": "20:48:41",
    "customer_id": "6f2aec8a-53c9-4acb-bf71-e1ae3f24ba6a",
    "items": [
      {
        "sku": "SKU00040",
        "product_name": "Biscuits Cerveau",
        "quantity": 3
      },
      {
        "sku": "SKU00083",
        "product_name": "Miel Mode",
        "quantity": 1
      },
      {
        "sku": "SKU00019",
        "product_name": "Liquide vaisselle Baisser",
        "quantity": 3
      }
    ]
  },
  {
    "order_id": "ORD-2026-01-12-S05-0048",
    "store_id": "STORE05",
    "order_date": "2026-01-12",
    "order_time": "20:19:31",
    "customer_id": "ed6f4ee3-e44e-4cd1-b8ef-a3bc9457f388",
    "items": [
      {
        "sku": "SKU00014",
        "product_name": "Eau En",
        "quantity": 3
      },
      {
        "sku": "SKU00052",
        "product_name": "Légumes surgelés Chambre",
        "quantity": 1
      },
      {
        "sku": "SKU00089",
        "product_name": "Biscuits Faute",
        "quantity": 2
      },
      {
        "sku": "SKU00049",
        "product_name": "Légumes surgelés Trésor",
        "quantity": 3
      }
    ]
  },
  {
    "order_id": "ORD-2026-01-12-S05-0049",
    "store_id": "STORE05",
    "order_date": "2026-01-12",
    "order_time": "9:42:12",
    "customer_id": "e9ebd446-2622-40d6-b23d-9820977e5877",
    "items": [
      {
        "sku": "SKU00007",
        "product_name": "Jus Beau",
        "quantity": 4
      },
      {
        "sku": "SKU00072",
        "product_name": "Crevettes Autorité",
        "quantity": 5
      },
      {
        "sku": "SKU00010",
        "product_name": "Déodorant Saisir",
        "quantity": 3
      },
      {
        "sku": "SKU00002",
        "product_name": "Crème Projet",
        "quantity": 4
      }
    ]
  },
  {
    "order_id": "ORD-2026-01-12-S05-0050",
    "store_id": "STORE05",
    "order_date": "2026-01-12",
    "order_time": "8:03:31",
    "customer_id": "6af31899-014c-43a1-a5f3-d46692de0df8",
    "items": [
      {
        "sku": "SKU00096",
        "product_name": "Lessive Point",
        "quantity": 4
      },
      {
        "sku": "SKU00007",
        "product_name": "Jus Beau",
        "quantity": 4
      }
    ]
  },
  {
    "order_id": "ORD-2026-01-12-S05-0051",
    "store_id": "STORE05",
    "order_date": "2026-01-12",
    "order_time": "18:10:04",
    "customer_id": "fdc419b2-0a41-4919-8b52-46f3faed5777",
    "items": [
      {
        "sku": "SKU00033",
        "product_name": "Sauce tomate Réunir",
        "quantity": 4
      },
      {
        "sku": "SKU00063",
        "product_name": "Thé Nommer",
        "quantity": 3
      },
      {
        "sku": "SKU00010",
        "product_name": "Déodorant Saisir",
        "quantity": 1
      },
      {
        "sku": "SKU00015",
        "product_name": "Crème Accuser",
        "quantity": 2
      }
    ]
  },
  {
    "order_id": "ORD-2026-01-12-S05-0052",
    "store_id": "STORE05",
    "order_date": "2026-01-12",
    "order_time": "9:48:36",
    "customer_id": "81145252-c4c3-4368-bbc5-1a50787cb0d3",
    "items": [
      {
        "sku": "SKU00037",
        "product_name": "Chocolat Peur",
        "quantity": 2
      },
      {
        "sku": "SKU00057",
        "product_name": "Lait Étrange",
        "quantity": 1
      },
      {
        "sku": "SKU00034",
        "product_name": "Eau Rien",
        "quantity": 2
      },
      {
        "sku": "SKU00040",
        "product_name": "Biscuits Cerveau",
        "quantity": 3
      },
      {
        "sku": "SKU00093",
        "product_name": "Lait infantile Vif",
        "quantity": 5
      },
      {
        "sku": "SKU00010",
        "product_name": "Déodorant Saisir",
        "quantity": 5
      },
      {
        "sku": "SKU00075",
        "product_name": "Couches Aide",
        "quantity": 5
      }
    ]
  },
  {
    "order_id": "ORD-2026-01-12-S05-0053",
    "store_id": "STORE05",
    "order_date": "2026-01-12",
    "order_time": "17:12:33",
    "customer_id": "64f22a7c-87f7-47fa-acfa-855f089b5b49",
    "items": [
      {
        "sku": "SKU00087",
        "product_name": "Confiture Absence",
        "quantity": 4
      },
      {
        "sku": "SKU00013",
        "product_name": "Petits pots Saison",
        "quantity": 2
      }
    ]
  },
  {
    "order_id": "ORD-2026-01-12-S05-0054",
    "store_id": "STORE05",
    "order_date": "2026-01-12",
    "order_time": "15:02:12",
    "customer_id": "b257e257-cc4a-402c-8f49-94e07ab16533",
    "items": [
      {
        "sku": "SKU00055",
        "product_name": "Conserves Inviter",
        "quantity": 3
      },
      {
        "sku": "SKU00020",
        "product_name": "Riz Ensuite",
        "quantity": 2
      },
      {
        "sku": "SKU00028",
        "product_name": "Carottes Tranquille",
        "quantity": 3
      },
      {
        "sku": "SKU00002",
        "product_name": "Crème Projet",
        "quantity": 3
      }
    ]
  },
  {
    "order_id": "ORD-2026-01-12-S05-0055",
    "store_id": "STORE05",
    "order_date": "2026-01-12",
    "order_time": "21:28:18",
    "customer_id": "7ecb002e-73d3-428c-9916-79d3d24025ea",
    "items": [
      {
        "sku": "SKU00004",
        "product_name": "Saumon Comme",
        "quantity": 5
      },
      {
        "sku": "SKU00022",
        "product_name": "Savon Approcher",
        "quantity": 5
      },
      {
        "sku": "SKU00028",
        "product_name": "Carottes Tranquille",
        "quantity": 1
      },
      {
        "sku": "SKU00016",
        "product_name": "Crème Boire",
        "quantity": 3
      },
      {
        "sku": "SKU00015",
        "product_name": "Crème Accuser",
        "quantity": 4
      }
    ]
  },
  {
    "order_id": "ORD-2026-01-12-S05-0056",
    "store_id": "STORE05",
    "order_date": "2026-01-12",
    "order_time": "8:28:47",
    "customer_id": "c0c9c3ed-8ef9-4060-9545-7c643d922952",
    "items": [
      {
        "sku": "SKU00058",
        "product_name": "Lingettes Distinguer",
        "quantity": 5
      },
      {
        "sku": "SKU00048",
        "product_name": "Biscuits Avancer",
        "quantity": 4
      },
      {
        "sku": "SKU00050",
        "product_name": "Oranges Terminer",
        "quantity": 2
      },
      {
        "sku": "SKU00093",
        "product_name": "Lait infantile Vif",
        "quantity": 2
      },
      {
        "sku": "SKU00001",
        "product_name": "Boeuf Oreille",
        "quantity": 3
      },
      {
        "sku": "SKU00057",
        "product_name": "Lait Étrange",
        "quantity": 1
      },
      {
        "sku": "SKU00056",
        "product_name": "Lait infantile Chien",
        "quantity": 1
      }
    ]
  },
  {
    "order_id": "ORD-2026-01-12-S05-0057",
    "store_id": "STORE05",
    "order_date": "2026-01-12",
    "order_time": "14:20:04",
    "customer_id": "68181f5b-bb56-488b-b172-ec53032e2730",
    "items": [
      {
        "sku": "SKU00012",
        "product_name": "Boeuf Entourer",
        "quantity": 5
      },
      {
        "sku": "SKU00062",
        "product_name": "Huile Côté",
        "quantity": 1
      },
      {
        "sku": "SKU00072",
        "product_name": "Crevettes Autorité",
        "quantity": 4
      },
      {
        "sku": "SKU00019",
        "product_name": "Liquide vaisselle Baisser",
        "quantity": 1
      },
      {
        "sku": "SKU00052",
        "product_name": "Légumes surgelés Chambre",
        "quantity": 5
      },
      {
        "sku": "SKU00074",
        "product_name": "Confiture Rassurer",
        "quantity": 3
      },
      {
        "sku": "SKU00092",
        "product_name": "Shampoing Nord",
        "quantity": 1
      },
      {
        "sku": "SKU00008",
        "product_name": "Riz Inutile",
        "quantity": 4
      }
    ]
  }
]